emmodel/__about__.py
emmodel/__init__.py
emmodel/cascade.py
emmodel/data.py
emmodel/model.py
emmodel/variable.py
emmodel-0.0.1.dist-info/LICENSE
emmodel-0.0.1.dist-info/METADATA
emmodel-0.0.1.dist-info/WHEEL
emmodel-0.0.1.dist-info/top_level.txt
emmodel-0.0.1.dist-info/RECORD
