Metadata-Version: 2.1
Name: emmodel
Version: 0.0.1
Summary: Excess mortality model
Home-page: https://github.com/ihmeuw-msca/emmodel
Author: IHME Math Sciences
Author-email: ihme.math.sciences@gmail.com
License: BSD-2-Clause License
Platform: UNKNOWN
Requires-Dist: regmod
Requires-Dist: matplotlib
Requires-Dist: pyyaml
Provides-Extra: dev
Requires-Dist: pytest ; extra == 'dev'
Requires-Dist: pytest-mock ; extra == 'dev'
Provides-Extra: docs
Provides-Extra: test
Requires-Dist: pytest ; extra == 'test'
Requires-Dist: pytest-mock ; extra == 'test'
